ca_key_cert_validator/__init__.py
ca_key_cert_validator/expections.py
ca_key_cert_validator/generators.py
ca_key_cert_validator/loaders.py
ca_key_cert_validator/savers.py
ca_key_cert_validator/structures.py
ca_key_cert_validator/validators.py
ca_key_cert_validator-0.1.3.dist-info/METADATA
ca_key_cert_validator-0.1.3.dist-info/WHEEL
ca_key_cert_validator-0.1.3.dist-info/RECORD
