Metadata-Version: 2.1
Name: ca-key-cert-validator
Version: 0.1.3
Summary: Toolset for validation of CA Key & Cert pair
License: GPL
Author: Volkov Mykhailo
Author-email: mvolkov83@gmail.com
Requires-Python: >=3.9,<4.0
Classifier: License :: Other/Proprietary License
Classifier: Programming Language :: Python :: 3
Classifier: Programming Language :: Python :: 3.9
Classifier: Programming Language :: Python :: 3.10
Classifier: Programming Language :: Python :: 3.11
Classifier: Programming Language :: Python :: 3.12
Requires-Dist: cryptography (>=42.0.2,<43.0.0)
